.coveragerc
.travis.yml
AUTHORS
CONTRIBUTING.rst
ChangeLog
LICENSE
MANIFEST.in
Makefile
Pipfile
Pipfile.lock
README.rst
mach.py
requirements.txt
requirements_dev.txt
setup.cfg
setup.py
tox.ini
docs/Makefile
docs/conf.py
docs/contributing.rst
docs/index.rst
docs/installation.rst
docs/make.bat
docs/readme.rst
docs/usage.rst
docs/_build/html/_static/ajax-loader.gif
docs/_build/html/_static/comment-bright.png
docs/_build/html/_static/comment-close.png
docs/_build/html/_static/comment.png
docs/_build/html/_static/down-pressed.png
docs/_build/html/_static/down.png
docs/_build/html/_static/file.png
docs/_build/html/_static/mach-logo.png
docs/_build/html/_static/minus.png
docs/_build/html/_static/plus.png
docs/_build/html/_static/up-pressed.png
docs/_build/html/_static/up.png
docs/_build/rinoh/.doctrees/images/f47fd389a409f0db2ace5ecc2cc193d51cf78aeb/mach-logo.jpg
docs/_static/mach-logo.png
docs/_static/mach-logo.svg
examples/bolt.py
examples/calc.py
examples/calc2.py
examples/calc3.py
examples/greet.py
examples/lftp.py
examples/short_options.py
examples/uftpd.py
examples/uftpd2.py
imgs/mach-logo.jpg
imgs/mach-logo.png
imgs/mach-logo.svg
mach.py.egg-info/PKG-INFO
mach.py.egg-info/SOURCES.txt
mach.py.egg-info/dependency_links.txt
mach.py.egg-info/not-zip-safe
mach.py.egg-info/pbr.json
mach.py.egg-info/top_level.txt
tests/test_mach.py