Metadata-Version: 2.1
Name: mach.py
Version: 0.4.4
Summary: Create CLI interfaces quickly
Home-page: https://github.com/oz123/mach
Author: Oz N Tiram
Author-email: oz.tiram@gmail.com
License: UNKNOWN
Platform: UNKNOWN
Classifier: Development Status :: 3 - Alpha
Classifier: Programming Language :: Python
Classifier: Programming Language :: Python :: 3.5
Classifier: Programming Language :: Python :: 3.6
Classifier: Intended Audience :: System Administrators
Classifier: Intended Audience :: Developers
Classifier: Operating System :: OS Independent
Classifier: License :: OSI Approved :: GNU Lesser General Public License v3 or later (LGPLv3+)
Classifier: Topic :: Software Development
License-File: LICENSE
License-File: AUTHORS
